mobio/__init__.py
mobio/libs/__init__.py
mobio/libs/filetype/__init__.py
mobio/libs/filetype/common.py
mobio/libs/filetype/file.py
mobio/libs/filetype/file_signature.json
mobio/libs/filetype/utils.py
m_filetype-0.0.1.dist-info/LICENSE
m_filetype-0.0.1.dist-info/METADATA
m_filetype-0.0.1.dist-info/WHEEL
m_filetype-0.0.1.dist-info/top_level.txt
m_filetype-0.0.1.dist-info/RECORD
